pymdmix_core/__init__.py
pymdmix_core/core.py
pymdmix_core/orm.py
pymdmix_core/parser.py
pymdmix_core/settings.py
pymdmix_core/plugin/__init__.py
pymdmix_core/plugin/base.py
pymdmix_core/plugin/crud.py
pymdmix_core-4.0.5.data/data/pymdmix/pymdmix_core.yml
pymdmix_core-4.0.5.data/scripts/mdmix
pymdmix_core-4.0.5.dist-info/LICENSE
pymdmix_core-4.0.5.dist-info/METADATA
pymdmix_core-4.0.5.dist-info/WHEEL
pymdmix_core-4.0.5.dist-info/top_level.txt
pymdmix_core-4.0.5.dist-info/RECORD
